PlotlyHuituMokuaiZhongwenZhinanDi1Qi/README.md
PlotlyHuituMokuaiZhongwenZhinanDi1Qi/__init__.py
PlotlyHuituMokuaiZhongwenZhinanDi1Qi/__main__.py
PlotlyHuituMokuaiZhongwenZhinanDi1Qi/file.pdf
PlotlyHuituMokuaiZhongwenZhinanDi1Qi/index.html
plotly_huitu_mokuai_zhongwen_zhinan_di_1_qi-2024.3.2.0.dist-info/METADATA
plotly_huitu_mokuai_zhongwen_zhinan_di_1_qi-2024.3.2.0.dist-info/WHEEL
plotly_huitu_mokuai_zhongwen_zhinan_di_1_qi-2024.3.2.0.dist-info/entry_points.txt
plotly_huitu_mokuai_zhongwen_zhinan_di_1_qi-2024.3.2.0.dist-info/top_level.txt
plotly_huitu_mokuai_zhongwen_zhinan_di_1_qi-2024.3.2.0.dist-info/RECORD
